ib002/__init__.py
ib002/sorting.py
ib002-1.0.0.dist-info/LICENSE
ib002-1.0.0.dist-info/METADATA
ib002-1.0.0.dist-info/WHEEL
ib002-1.0.0.dist-info/RECORD
