Metadata-Version: 2.1
Name: ib002
Version: 1.0.0
Summary: sorting algorithms
License: MIT
Author: Michal Šoltis
Author-email: msoltis@redhat.com
Requires-Python: >=3.11,<4.0
Classifier: License :: OSI Approved :: MIT License
Classifier: Programming Language :: Python :: 3
Classifier: Programming Language :: Python :: 3.11
